<InterfaceView version="1.2" asn1file="obc-firmware.acn" mscfile="/home/taste/obc-model/obc-model.msc" UiFile="interfaceview.ui.xml">
<Function id="{296ebcb1-5066-40f8-88b3-d0e3eead9b3c}" name="eps_subsystem" is_type="NO" language="SDL" default_implementation="default" fixed_system_element="NO" required_system_element="NO" instances_max="1" instances_min="1" startup_priority="1">
    <Property name="TASTE_IV_Properties::Default_Codegen" value="Ada"/>
<Provided_Interface id="{121cd45d-1a51-4c1a-85b2-49236537fc18}" name="change_eps_mode" kind="Sporadic" enable_multicast="true" layer="default" required_system_element="NO" is_simulink_interface="false" stack_size="340" queue_size="1" wcet="0" priority="1" miat="0">
    <Input_Parameter name="target_eps_mode" type="EPS-Mode-T" encoding="NATIVE"/>
</Provided_Interface>

<Required_Interface id="{d046c2f5-f383-421d-bb3c-de9514fb4119}" name="report_eps_mode_status" kind="Sporadic" enable_multicast="true" layer="default" required_system_element="NO" is_simulink_interface="false" stack_size="340" queue_size="1" wcet="0" priority="1" miat="0">
    <Input_Parameter name="eps_mode_status_report" type="EPS-Mode-Status-Report-T" encoding="NATIVE"/>
    <Property name="Taste::InheritPI" value="true"/>
    <Property name="Taste::Autonamed" value="true"/>
</Required_Interface>

<Function id="{6b5e60bb-4c3e-4f13-8cf9-bba8fee5b5ac}" name="eps_mode_tracker" is_type="NO" is_visible="true" language="SDL" default_implementation="default" fixed_system_element="NO" required_system_element="NO" instances_max="1" instances_min="1" startup_priority="1" FPGA_Configurations="">
    <Property name="TASTE_IV_Properties::Default_Codegen" value="Ada"/>
<Provided_Interface id="{d53edff3-56cf-4adb-aaff-4005bb8b3bf4}" name="change_eps_mode" kind="Sporadic" enable_multicast="true" layer="default" required_system_element="NO" is_simulink_interface="false" stack_size="340" queue_size="1" wcet="0" priority="1" miat="0">
    <Input_Parameter name="target_eps_mode" type="EPS-Mode-T" encoding="NATIVE"/>
</Provided_Interface>

<Required_Interface id="{2187ff8f-7ea0-4ac6-a156-75d6546ae6e8}" name="report_eps_mode_status" kind="Sporadic" enable_multicast="true" layer="default" required_system_element="NO" is_simulink_interface="false" stack_size="340" queue_size="1" wcet="0" priority="1" miat="0">
    <Input_Parameter name="eps_mode_status_report" type="EPS-Mode-Status-Report-T" encoding="NATIVE"/>
    <Property name="Taste::InheritPI" value="true"/>
    <Property name="Taste::Autonamed" value="true"/>
</Required_Interface>

    <Implementations>
        <Implementation name="default" language="SDL"/>
    </Implementations>
</Function>

<Connection id="{904ac767-ac77-4fdb-8100-e8bb376940f7}" name="eps_subsystem_change_eps_mode____eps_mode_tracker_change_eps_mode" required_system_element="NO">
    <Source func_name="eps_subsystem" pi_name="change_eps_mode" />
    <Target func_name="eps_mode_tracker" pi_name="change_eps_mode" />
</Connection>

<Connection id="{3a0733d4-ef78-4748-a6ac-c3103febd221}" name="eps_mode_tracker_report_eps_mode_status____eps_subsystem_report_eps_mode_status" required_system_element="NO">
    <Source func_name="eps_mode_tracker" ri_name="report_eps_mode_status" />
    <Target func_name="eps_subsystem" ri_name="report_eps_mode_status" />
</Connection>

    <Implementations>
        <Implementation name="default" language="SDL"/>
    </Implementations>
</Function>

<Function id="{4c76f858-03de-4264-8ff7-1b3a466f1eb8}" name="obc_subsystem" is_type="NO" language="SDL" default_implementation="default" fixed_system_element="NO" required_system_element="NO" instances_max="1" instances_min="1" startup_priority="1">
    <Property name="TASTE_IV_Properties::Default_Codegen" value="Ada"/>
<Provided_Interface id="{8974cb23-8b1f-4b4f-aab1-629ede19a62d}" name="tc_change_mission_mode" kind="Sporadic" enable_multicast="true" layer="default" required_system_element="NO" is_simulink_interface="false" stack_size="1024" queue_size="1" wcet="0" priority="1" miat="0">
    <Input_Parameter name="mission_mode_change_tc" type="Mission-Mode-Change-TC-T" encoding="UPER"/>
</Provided_Interface>

<Provided_Interface id="{c344a643-914e-4efa-bdfc-fe5da8f10635}" name="report_deployer_mode_status" kind="Sporadic" enable_multicast="true" layer="default" required_system_element="NO" is_simulink_interface="false" stack_size="1024" queue_size="1" wcet="0" priority="1" miat="0">
    <Input_Parameter name="deployer_mode_status_report" type="Deployer-Mode-Status-Report-T" encoding="NATIVE"/>
</Provided_Interface>

<Provided_Interface id="{fae30a64-19b1-46a9-96b2-0b0574c2c947}" name="report_comms_mode_status" kind="Sporadic" enable_multicast="true" layer="default" required_system_element="NO" is_simulink_interface="false" stack_size="340" queue_size="1" wcet="0" priority="1" miat="0">
    <Input_Parameter name="comms_mode_status_report" type="Comms-Mode-Status-Report-T" encoding="NATIVE"/>
</Provided_Interface>

<Provided_Interface id="{dfd7e3db-012f-41d1-8efc-ecfc44c00380}" name="report_pipeline_mode_status" kind="Sporadic" enable_multicast="true" layer="default" required_system_element="NO" is_simulink_interface="false" stack_size="340" queue_size="1" wcet="0" priority="1" miat="0">
    <Input_Parameter name="pipeline_mode_status_report" type="Pipeline-Mode-Status-Report-T" encoding="NATIVE"/>
</Provided_Interface>

<Provided_Interface id="{d400d17b-3c9b-4bfb-b0bd-cc95861e5bdb}" name="report_eps_mode_status" kind="Sporadic" enable_multicast="true" layer="default" required_system_element="NO" is_simulink_interface="false" stack_size="340" queue_size="1" wcet="0" priority="1" miat="0">
    <Input_Parameter name="eps_mode_status_report" type="EPS-Mode-Status-Report-T" encoding="NATIVE"/>
</Provided_Interface>

<Provided_Interface id="{dd6b4966-9d5d-497b-b071-ed1357e651f6}" name="report_payload_mode_status" kind="Sporadic" enable_multicast="true" layer="default" required_system_element="NO" is_simulink_interface="false" stack_size="340" queue_size="1" wcet="0" priority="1" miat="0">
    <Input_Parameter name="payload_mode_status_report" type="Payload-Mode-Status-Report-T" encoding="NATIVE"/>
</Provided_Interface>

<Provided_Interface id="{c3f00440-ff63-4681-91ac-365f8761b6f4}" name="report_adcs_mode_status" kind="Sporadic" enable_multicast="true" layer="default" required_system_element="NO" is_simulink_interface="false" stack_size="340" queue_size="1" wcet="0" priority="1" miat="0">
    <Input_Parameter name="adcs_mode_status_report" type="ADCS-Mode-Status-Report-T" encoding="NATIVE"/>
</Provided_Interface>

<Required_Interface id="{fd02c6b8-e242-4467-90f2-19d951bb7689}" name="report_mission_mode_change" kind="Sporadic" is_visible="true" enable_multicast="true" layer="default" required_system_element="NO" is_simulink_interface="false" stack_size="1024" queue_size="16" wcet="0" priority="1" miat="0">
    <Input_Parameter name="mission_mode_change_report" type="Mission-Mode-Change-Report-T" encoding="UPER"/>
    <Property name="Taste::InheritPI" value="true"/>
    <Property name="Taste::Autonamed" value="true"/>
</Required_Interface>

<Required_Interface id="{103fbb9c-7a9a-4875-bbbf-597e5cba40dc}" name="change_comms_mode" kind="Sporadic" enable_multicast="true" layer="default" required_system_element="NO" is_simulink_interface="false" stack_size="340" queue_size="1" wcet="0" priority="1" miat="0">
    <Input_Parameter name="target_comms_mode" type="Comms-Mode-T" encoding="NATIVE"/>
    <Property name="Taste::InheritPI" value="true"/>
    <Property name="Taste::Autonamed" value="true"/>
</Required_Interface>

<Required_Interface id="{a19e9c6f-571c-446d-ac87-77b87bd725a4}" name="change_deployer_mode" kind="Sporadic" enable_multicast="true" layer="default" required_system_element="NO" is_simulink_interface="false" stack_size="340" queue_size="1" wcet="0" priority="1" miat="0">
    <Input_Parameter name="target_deployer_mode" type="Deployer-Mode-T" encoding="NATIVE"/>
    <Property name="Taste::InheritPI" value="true"/>
    <Property name="Taste::Autonamed" value="true"/>
</Required_Interface>

<Required_Interface id="{c66f7c7e-5f03-4f32-ab44-d287b024a1f7}" name="change_eps_mode" kind="Sporadic" enable_multicast="true" layer="default" required_system_element="NO" is_simulink_interface="false" stack_size="340" queue_size="1" wcet="0" priority="1" miat="0">
    <Input_Parameter name="target_eps_mode" type="EPS-Mode-T" encoding="NATIVE"/>
    <Property name="Taste::InheritPI" value="true"/>
    <Property name="Taste::Autonamed" value="true"/>
</Required_Interface>

<Required_Interface id="{382679aa-f03c-4cbf-a7b8-0f5b4e2e0133}" name="change_pipeline_mode" kind="Sporadic" enable_multicast="true" layer="default" required_system_element="NO" is_simulink_interface="false" stack_size="340" queue_size="1" wcet="0" priority="1" miat="0">
    <Input_Parameter name="target_pipeline_mode" type="Pipeline-Mode-T" encoding="NATIVE"/>
    <Property name="Taste::InheritPI" value="true"/>
    <Property name="Taste::Autonamed" value="true"/>
</Required_Interface>

<Required_Interface id="{814bb92d-eba3-4600-b6c2-d1ed5b85cbb5}" name="change_payload_mode" kind="Sporadic" enable_multicast="true" layer="default" required_system_element="NO" is_simulink_interface="false" stack_size="340" queue_size="1" wcet="0" priority="1" miat="0">
    <Input_Parameter name="target_payload_mode" type="Payload-Mode-T" encoding="NATIVE"/>
    <Property name="Taste::InheritPI" value="true"/>
    <Property name="Taste::Autonamed" value="true"/>
</Required_Interface>

<Required_Interface id="{613df257-6ae5-499f-853c-f157482b79cc}" name="change_adcs_mode" kind="Sporadic" enable_multicast="true" layer="default" required_system_element="NO" is_simulink_interface="false" stack_size="340" queue_size="1" wcet="0" priority="1" miat="0">
    <Input_Parameter name="target_adcs_mode" type="ADCS-Mode-T" encoding="NATIVE"/>
    <Property name="Taste::InheritPI" value="true"/>
    <Property name="Taste::Autonamed" value="true"/>
</Required_Interface>

<Function id="{972e8e24-275f-4a0e-b469-39f22bf2547f}" name="HAL" is_type="NO" is_visible="true" language="SDL" default_implementation="x86" fixed_system_element="NO" required_system_element="NO" instances_max="1" instances_min="1" startup_priority="1" FPGA_Configurations="">
    <Property name="TASTE_IV_Properties::Default_Codegen" value="Ada"/>
<Provided_Interface id="{bb72fda3-b26b-440a-8320-300a1328ce27}" name="blink_led" kind="Cyclic" is_visible="true" enable_multicast="true" layer="default" required_system_element="NO" is_simulink_interface="false" stack_size="256" period="500" wcet="200" priority="1" dispatch_offset="0">
</Provided_Interface>

<Provided_Interface id="{51d88f2f-533a-4b8b-bf54-9b00b639836e}" name="set_led" kind="Protected" is_visible="true" enable_multicast="true" layer="default" required_system_element="NO" is_simulink_interface="false" wcet="0">
    <Input_Parameter name="val" type="T-Boolean" encoding="NATIVE"/>
</Provided_Interface>

    <Implementations>
        <Implementation name="msp430" language="C"/>
        <Implementation name="x86" language="SDL"/>
    </Implementations>
</Function>

<Function id="{cff3dce7-920c-4848-971c-5d3de03c1dbd}" name="mission_mode_change_tc_handler" is_type="NO" is_visible="true" language="SDL" default_implementation="default" fixed_system_element="NO" required_system_element="NO" instances_max="1" instances_min="1" startup_priority="1" FPGA_Configurations="">
    <Property name="TASTE_IV_Properties::Default_Codegen" value="Ada"/>
<Provided_Interface id="{b6cee5cd-ea42-46c7-be4e-790460789f5a}" name="tc_change_mission_mode" kind="Sporadic" is_visible="true" enable_multicast="true" layer="default" required_system_element="NO" is_simulink_interface="false" stack_size="1024" queue_size="16" wcet="0" priority="1" miat="0">
    <Input_Parameter name="mission_mode_change_tc" type="Mission-Mode-Change-TC-T" encoding="UPER"/>
</Provided_Interface>

<Provided_Interface id="{7d433119-0bf4-4574-983c-8879e1bfecac}" name="relay_system_mode_status_report" kind="Sporadic" is_visible="true" enable_multicast="true" layer="default" required_system_element="NO" is_simulink_interface="false" stack_size="512" queue_size="1" wcet="0" priority="1" miat="0">
    <Input_Parameter name="system_mode_status_report" type="System-Mode-Status-Report-T" encoding="NATIVE"/>
</Provided_Interface>

<Required_Interface id="{0cad64b8-9497-4385-bf6a-5c0b970741c3}" name="report_mission_mode_change" kind="Sporadic" is_visible="true" enable_multicast="true" layer="default" required_system_element="NO" is_simulink_interface="false" stack_size="1024" queue_size="16" wcet="0" priority="1" miat="0">
    <Input_Parameter name="mission_mode_change_report" type="Mission-Mode-Change-Report-T" encoding="UPER"/>
    <Property name="Taste::InheritPI" value="true"/>
    <Property name="Taste::Autonamed" value="true"/>
</Required_Interface>

<Required_Interface id="{206b530d-0d26-4b3f-9920-1728594a7b35}" name="change_system_mode" kind="Protected" enable_multicast="true" layer="default" required_system_element="NO" is_simulink_interface="false" wcet="0">
    <Input_Parameter name="target_system_mode_in" type="System-Mode-T" encoding="NATIVE"/>
    <Property name="Taste::InheritPI" value="true"/>
    <Property name="Taste::Autonamed" value="true"/>
</Required_Interface>

    <Implementations>
        <Implementation name="default" language="SDL"/>
    </Implementations>
</Function>

<Function id="{420eaf7a-1895-4d1b-b2e5-c7f40bcaad42}" name="system_mode_manager" is_type="NO" is_visible="true" language="SDL" default_implementation="default" fixed_system_element="NO" required_system_element="NO" instances_max="1" instances_min="1" startup_priority="1" FPGA_Configurations="">
    <Property name="TASTE_IV_Properties::Default_Codegen" value="Ada"/>
<Provided_Interface id="{4e73e9bb-a965-407e-b381-c7a36f015d0d}" name="report_deployer_mode_status" kind="Sporadic" enable_multicast="true" layer="default" required_system_element="NO" is_simulink_interface="false" stack_size="340" queue_size="1" wcet="0" priority="1" miat="0">
    <Input_Parameter name="deployer_mode_status_report" type="Deployer-Mode-Status-Report-T" encoding="NATIVE"/>
</Provided_Interface>

<Provided_Interface id="{613158a6-a19d-4b90-91b7-0276c13dde4a}" name="report_pipeline_mode_status" kind="Sporadic" enable_multicast="true" layer="default" required_system_element="NO" is_simulink_interface="false" stack_size="340" queue_size="1" wcet="0" priority="1" miat="0">
    <Input_Parameter name="pipeline_mode_status_report" type="Pipeline-Mode-Status-Report-T" encoding="NATIVE"/>
</Provided_Interface>

<Provided_Interface id="{947e6d6f-ae3f-4d2e-bc4c-b74b6ba7e138}" name="change_system_mode" kind="Protected" enable_multicast="true" layer="default" required_system_element="NO" is_simulink_interface="false" wcet="0">
    <Input_Parameter name="target_system_mode_in" type="System-Mode-T" encoding="NATIVE"/>
</Provided_Interface>

<Provided_Interface id="{eeda89b3-5168-472e-9c4a-7c8e56e792b9}" name="report_eps_mode_status" kind="Sporadic" enable_multicast="true" layer="default" required_system_element="NO" is_simulink_interface="false" stack_size="340" queue_size="1" wcet="0" priority="1" miat="0">
    <Input_Parameter name="eps_mode_status_report" type="EPS-Mode-Status-Report-T" encoding="NATIVE"/>
</Provided_Interface>

<Provided_Interface id="{5b27bee0-8efd-4932-97ee-a4b3ba34cd80}" name="report_comms_mode_status" kind="Sporadic" enable_multicast="true" layer="default" required_system_element="NO" is_simulink_interface="false" stack_size="340" queue_size="1" wcet="0" priority="1" miat="0">
    <Input_Parameter name="comms_mode_status_report" type="Comms-Mode-Status-Report-T" encoding="NATIVE"/>
</Provided_Interface>

<Provided_Interface id="{7eff5865-98fd-4c98-903a-fdf539ea7433}" name="report_adcs_mode_status" kind="Sporadic" enable_multicast="true" layer="default" required_system_element="NO" is_simulink_interface="false" stack_size="340" queue_size="1" wcet="0" priority="1" miat="0">
    <Input_Parameter name="adcs_mode_status_report" type="ADCS-Mode-Status-Report-T" encoding="NATIVE"/>
</Provided_Interface>

<Provided_Interface id="{f04b4f3c-06ce-4a4f-b47e-4511288de870}" name="report_payload_mode_status" kind="Sporadic" enable_multicast="true" layer="default" required_system_element="NO" is_simulink_interface="false" stack_size="340" queue_size="1" wcet="0" priority="1" miat="0">
    <Input_Parameter name="payload_mode_status_report" type="Payload-Mode-Status-Report-T" encoding="NATIVE"/>
</Provided_Interface>

<Required_Interface id="{cce8e867-4c7e-41b4-be16-fd1dad468143}" name="set_led" kind="Protected" is_visible="true" enable_multicast="true" layer="default" required_system_element="NO" is_simulink_interface="false" wcet="0">
    <Input_Parameter name="val" type="T-Boolean" encoding="NATIVE"/>
    <Property name="Taste::InheritPI" value="true"/>
    <Property name="Taste::Autonamed" value="true"/>
</Required_Interface>

<Required_Interface id="{bc17c57d-6cb8-470f-80b4-048282cdfc4d}" name="change_eps_mode" kind="Sporadic" enable_multicast="true" layer="default" required_system_element="NO" is_simulink_interface="false" stack_size="340" queue_size="1" wcet="0" priority="1" miat="0">
    <Input_Parameter name="target_eps_mode" type="EPS-Mode-T" encoding="NATIVE"/>
    <Property name="Taste::InheritPI" value="true"/>
    <Property name="Taste::Autonamed" value="true"/>
</Required_Interface>

<Required_Interface id="{03c977cc-0b52-4290-9852-42eff6abc800}" name="change_comms_mode" kind="Sporadic" enable_multicast="true" layer="default" required_system_element="NO" is_simulink_interface="false" stack_size="340" queue_size="1" wcet="0" priority="1" miat="0">
    <Input_Parameter name="target_comms_mode" type="Comms-Mode-T" encoding="NATIVE"/>
    <Property name="Taste::InheritPI" value="true"/>
    <Property name="Taste::Autonamed" value="true"/>
</Required_Interface>

<Required_Interface id="{287f4fe0-2289-49a8-ac66-dff3e022810d}" name="change_deployer_mode" kind="Sporadic" enable_multicast="true" layer="default" required_system_element="NO" is_simulink_interface="false" stack_size="340" queue_size="1" wcet="0" priority="1" miat="0">
    <Input_Parameter name="target_deployer_mode" type="Deployer-Mode-T" encoding="NATIVE"/>
    <Property name="Taste::InheritPI" value="true"/>
    <Property name="Taste::Autonamed" value="true"/>
</Required_Interface>

<Required_Interface id="{40fe6905-24c1-4fee-8533-286e85688a0d}" name="change_adcs_mode" kind="Sporadic" enable_multicast="true" layer="default" required_system_element="NO" is_simulink_interface="false" stack_size="340" queue_size="1" wcet="0" priority="1" miat="0">
    <Input_Parameter name="target_adcs_mode" type="ADCS-Mode-T" encoding="NATIVE"/>
    <Property name="Taste::InheritPI" value="true"/>
    <Property name="Taste::Autonamed" value="true"/>
</Required_Interface>

<Required_Interface id="{54d4ca84-18fb-4d57-a90e-09e9f2a9d0bc}" name="change_payload_mode" kind="Sporadic" enable_multicast="true" layer="default" required_system_element="NO" is_simulink_interface="false" stack_size="340" queue_size="1" wcet="0" priority="1" miat="0">
    <Input_Parameter name="target_payload_mode" type="Payload-Mode-T" encoding="NATIVE"/>
    <Property name="Taste::InheritPI" value="true"/>
    <Property name="Taste::Autonamed" value="true"/>
</Required_Interface>

<Required_Interface id="{b376c999-6c5b-43b6-b95c-883b9a7399d3}" name="change_pipeline_mode" kind="Sporadic" enable_multicast="true" layer="default" required_system_element="NO" is_simulink_interface="false" stack_size="340" queue_size="1" wcet="0" priority="1" miat="0">
    <Input_Parameter name="target_pipeline_mode" type="Pipeline-Mode-T" encoding="NATIVE"/>
    <Property name="Taste::InheritPI" value="true"/>
    <Property name="Taste::Autonamed" value="true"/>
</Required_Interface>

<Required_Interface id="{550e5102-2dad-4ae1-854f-3268932a78e4}" name="relay_system_mode_status_report" kind="Sporadic" is_visible="true" enable_multicast="true" layer="default" required_system_element="NO" is_simulink_interface="false" stack_size="512" queue_size="1" wcet="0" priority="1" miat="0">
    <Input_Parameter name="system_mode_status_report" type="System-Mode-Status-Report-T" encoding="NATIVE"/>
    <Property name="Taste::InheritPI" value="true"/>
    <Property name="Taste::Autonamed" value="true"/>
</Required_Interface>

    <Implementations>
        <Implementation name="default" language="SDL"/>
        <Implementation name="test_subsystem_mode_change_validation" language="SDL"/>
    </Implementations>
</Function>

<Connection id="{91504de8-9918-4a93-9275-ff9adfa6ff32}" required_system_element="NO">
    <Source func_name="mission_mode_change_tc_handler" ri_name="change_system_mode" />
    <Target func_name="system_mode_manager" pi_name="change_system_mode" />
</Connection>

<Connection id="{ce5c8251-a29a-44a6-a0c8-7ba1fe7c871e}" required_system_element="NO">
    <Source func_name="system_mode_manager" ri_name="relay_system_mode_status_report" />
    <Target func_name="mission_mode_change_tc_handler" pi_name="relay_system_mode_status_report" />
</Connection>

<Connection id="{8ca5e8f6-2e86-4f41-b58f-d7cab251625b}" name="obc_subsystem_tc_change_mission_mode____mission_mode_change_tc_handler_tc_change_mission_mode" required_system_element="NO">
    <Source func_name="obc_subsystem" pi_name="tc_change_mission_mode" />
    <Target func_name="mission_mode_change_tc_handler" pi_name="tc_change_mission_mode" />
</Connection>

<Connection id="{38fe1fa6-5055-4d27-9afe-1f712c73ad08}" name="mission_mode_change_tc_handler_report_mission_mode_change____obc_subsystem_report_mission_mode_change" required_system_element="NO">
    <Source func_name="mission_mode_change_tc_handler" ri_name="report_mission_mode_change" />
    <Target func_name="obc_subsystem" ri_name="report_mission_mode_change" />
</Connection>

<Connection id="{2dcdfa54-dc3a-4ddc-8a26-805207cd63ca}" name="obc_subsystem_report_deployer_mode_status____system_mode_manager_report_deployer_mode_status" required_system_element="NO">
    <Source func_name="obc_subsystem" pi_name="report_deployer_mode_status" />
    <Target func_name="system_mode_manager" pi_name="report_deployer_mode_status" />
</Connection>

<Connection id="{2915d13a-1e80-41f0-982f-3f68f9a54ffe}" name="obc_subsystem_report_comms_mode_status____system_mode_manager_report_comms_mode_status" required_system_element="NO">
    <Source func_name="obc_subsystem" pi_name="report_comms_mode_status" />
    <Target func_name="system_mode_manager" pi_name="report_comms_mode_status" />
</Connection>

<Connection id="{e51aca01-d80e-45fc-909b-52094247e367}" name="system_mode_manager_change_comms_mode____obc_subsystem_change_comms_mode" required_system_element="NO">
    <Source func_name="system_mode_manager" ri_name="change_comms_mode" />
    <Target func_name="obc_subsystem" ri_name="change_comms_mode" />
</Connection>

<Connection id="{54543d0d-a704-4ee6-9be2-68f4fe87cef4}" name="system_mode_manager_change_deployer_mode____obc_subsystem_change_deployer_mode" required_system_element="NO">
    <Source func_name="system_mode_manager" ri_name="change_deployer_mode" />
    <Target func_name="obc_subsystem" ri_name="change_deployer_mode" />
</Connection>

<Connection id="{ff6d5b97-0918-4ffa-bcd4-a8280cdabe49}" name="obc_subsystem_report_pipeline_mode_status____system_mode_manager_report_pipeline_mode_status" required_system_element="NO">
    <Source func_name="obc_subsystem" pi_name="report_pipeline_mode_status" />
    <Target func_name="system_mode_manager" pi_name="report_pipeline_mode_status" />
</Connection>

<Connection id="{e43c7b1b-a8af-4206-bc46-557cf001dd0c}" required_system_element="NO">
    <Source func_name="system_mode_manager" ri_name="set_led" />
    <Target func_name="HAL" pi_name="set_led" />
</Connection>

<Connection id="{54be6e97-882f-4e89-995c-5600b139941a}" name="system_mode_manager_change_eps_mode____obc_subsystem_change_eps_mode" required_system_element="NO">
    <Source func_name="system_mode_manager" ri_name="change_eps_mode" />
    <Target func_name="obc_subsystem" ri_name="change_eps_mode" />
</Connection>

<Connection id="{bab8ddb4-b17f-4b84-9516-a00af829627c}" name="obc_subsystem_report_eps_mode_status____system_mode_manager_report_eps_mode_status" required_system_element="NO">
    <Source func_name="obc_subsystem" pi_name="report_eps_mode_status" />
    <Target func_name="system_mode_manager" pi_name="report_eps_mode_status" />
</Connection>

<Connection id="{37aa01a0-ffc1-4a72-9fc3-1c136068372f}" name="system_mode_manager_change_pipeline_mode____obc_subsystem_change_pipeline_mode" required_system_element="NO">
    <Source func_name="system_mode_manager" ri_name="change_pipeline_mode" />
    <Target func_name="obc_subsystem" ri_name="change_pipeline_mode" />
</Connection>

<Connection id="{77df8717-680b-404e-856b-2ce5f7123263}" name="obc_subsystem_report_payload_mode_status____system_mode_manager_report_payload_mode_status" required_system_element="NO">
    <Source func_name="obc_subsystem" pi_name="report_payload_mode_status" />
    <Target func_name="system_mode_manager" pi_name="report_payload_mode_status" />
</Connection>

<Connection id="{c230dfc1-f59d-4a96-abd7-9ca65f780dc7}" name="system_mode_manager_change_payload_mode____obc_subsystem_change_payload_mode" required_system_element="NO">
    <Source func_name="system_mode_manager" ri_name="change_payload_mode" />
    <Target func_name="obc_subsystem" ri_name="change_payload_mode" />
</Connection>

<Connection id="{0bef328d-fb23-44cc-a6dc-7b9e0d2662c7}" name="system_mode_manager_change_adcs_mode____obc_subsystem_change_adcs_mode" required_system_element="NO">
    <Source func_name="system_mode_manager" ri_name="change_adcs_mode" />
    <Target func_name="obc_subsystem" ri_name="change_adcs_mode" />
</Connection>

<Connection id="{b75b9e12-2a60-4181-a270-48ec2a01d6e6}" name="obc_subsystem_report_adcs_mode_status____system_mode_manager_report_adcs_mode_status" required_system_element="NO">
    <Source func_name="obc_subsystem" pi_name="report_adcs_mode_status" />
    <Target func_name="system_mode_manager" pi_name="report_adcs_mode_status" />
</Connection>

    <Implementations>
        <Implementation name="default" language="SDL"/>
    </Implementations>
</Function>

<Function id="{08f78e57-51be-456e-97bb-ba95b57b2566}" name="pipeline_subsystem" is_type="NO" language="SDL" default_implementation="default" fixed_system_element="NO" required_system_element="NO" instances_max="1" instances_min="1" startup_priority="1">
    <Property name="TASTE_IV_Properties::Default_Codegen" value="Ada"/>
<Provided_Interface id="{6c61c9cd-9a34-475e-8850-2b8af6015c5b}" name="change_pipeline_mode" kind="Sporadic" enable_multicast="true" layer="default" required_system_element="NO" is_simulink_interface="false" stack_size="340" queue_size="1" wcet="0" priority="1" miat="0">
    <Input_Parameter name="target_pipeline_mode" type="Pipeline-Mode-T" encoding="NATIVE"/>
</Provided_Interface>

<Required_Interface id="{3529da38-0425-44a0-a778-0ae3e1f218fb}" name="report_pipeline_mode_status" kind="Sporadic" enable_multicast="true" layer="default" required_system_element="NO" is_simulink_interface="false" stack_size="340" queue_size="1" wcet="0" priority="1" miat="0">
    <Input_Parameter name="pipeline_mode_status_report" type="Pipeline-Mode-Status-Report-T" encoding="NATIVE"/>
    <Property name="Taste::InheritPI" value="true"/>
    <Property name="Taste::Autonamed" value="true"/>
</Required_Interface>

<Function id="{c6448cb3-50f4-4ff0-a4f6-4b2a7773901f}" name="pipeline_mode_tracker" is_type="NO" is_visible="true" language="SDL" default_implementation="default" fixed_system_element="NO" required_system_element="NO" instances_max="1" instances_min="1" startup_priority="1" FPGA_Configurations="">
    <Property name="TASTE_IV_Properties::Default_Codegen" value="Ada"/>
<Provided_Interface id="{4c310b47-ef29-46e3-8769-4dabf278b75f}" name="change_pipeline_mode" kind="Sporadic" enable_multicast="true" layer="default" required_system_element="NO" is_simulink_interface="false" stack_size="340" queue_size="1" wcet="0" priority="1" miat="0">
    <Input_Parameter name="target_pipeline_mode" type="Pipeline-Mode-T" encoding="NATIVE"/>
</Provided_Interface>

<Required_Interface id="{fdc4ca19-be8f-438b-ba80-b693a331e5b7}" name="report_pipeline_mode_status" kind="Sporadic" enable_multicast="true" layer="default" required_system_element="NO" is_simulink_interface="false" stack_size="340" queue_size="1" wcet="0" priority="1" miat="0">
    <Input_Parameter name="pipeline_mode_status_report" type="Pipeline-Mode-Status-Report-T" encoding="NATIVE"/>
    <Property name="Taste::InheritPI" value="true"/>
    <Property name="Taste::Autonamed" value="true"/>
</Required_Interface>

    <Implementations>
        <Implementation name="default" language="SDL"/>
    </Implementations>
</Function>

<Connection id="{058ea604-fa93-47ec-94ac-c1184d1f5461}" name="pipeline_subsystem_change_pipeline_mode____pipeline_mode_tracker_change_pipeline_mode" required_system_element="NO">
    <Source func_name="pipeline_subsystem" pi_name="change_pipeline_mode" />
    <Target func_name="pipeline_mode_tracker" pi_name="change_pipeline_mode" />
</Connection>

<Connection id="{746c4e63-5886-4223-908b-513d98eba474}" name="pipeline_mode_tracker_report_pipeline_mode_status____pipeline_subsystem_report_pipeline_mode_status" required_system_element="NO">
    <Source func_name="pipeline_mode_tracker" ri_name="report_pipeline_mode_status" />
    <Target func_name="pipeline_subsystem" ri_name="report_pipeline_mode_status" />
</Connection>

    <Implementations>
        <Implementation name="default" language="SDL"/>
    </Implementations>
</Function>

<Function id="{88fc8749-5905-433c-af04-b933b456c849}" name="gs_gui" is_type="NO" is_visible="true" language="GUI" default_implementation="default" fixed_system_element="NO" required_system_element="NO" instances_max="1" instances_min="1" startup_priority="1" FPGA_Configurations="">
    <Property name="TASTE_IV_Properties::Default_Codegen" value="Ada"/>
<Provided_Interface id="{0cb9d1c5-84bc-42c5-afc6-122a06df302a}" name="report_mission_mode_change" kind="Sporadic" is_visible="true" enable_multicast="true" layer="default" required_system_element="NO" is_simulink_interface="false" stack_size="1024" queue_size="16" wcet="0" priority="1" miat="0">
    <Input_Parameter name="mission_mode_change_report" type="Mission-Mode-Change-Report-T" encoding="UPER"/>
</Provided_Interface>

<Required_Interface id="{929d2509-c0aa-4dbc-9974-2a6bdcf442c9}" name="tc_change_mission_mode" kind="Sporadic" enable_multicast="true" layer="default" required_system_element="NO" is_simulink_interface="false" stack_size="1024" queue_size="1" wcet="0" priority="1" miat="0">
    <Input_Parameter name="mission_mode_change_tc" type="Mission-Mode-Change-TC-T" encoding="UPER"/>
    <Property name="Taste::InheritPI" value="true"/>
    <Property name="Taste::Autonamed" value="true"/>
</Required_Interface>

    <Implementations>
        <Implementation name="default" language="GUI"/>
    </Implementations>
</Function>

<Function id="{2944a7a3-56e6-4c80-8fce-fb6465be9875}" name="comms_subsystem" is_type="NO" language="SDL" default_implementation="default" fixed_system_element="NO" required_system_element="NO" instances_max="1" instances_min="1" startup_priority="1">
    <Property name="TASTE_IV_Properties::Default_Codegen" value="Ada"/>
<Provided_Interface id="{9e9f7d8b-5a3d-461b-933e-3c9b4042af71}" name="change_comms_mode" kind="Sporadic" enable_multicast="true" layer="default" required_system_element="NO" is_simulink_interface="false" stack_size="340" queue_size="1" wcet="0" priority="1" miat="0">
    <Input_Parameter name="target_comms_mode" type="Comms-Mode-T" encoding="NATIVE"/>
</Provided_Interface>

<Required_Interface id="{208fd698-2690-432b-9f8b-b3dc94576a5f}" name="report_comms_mode_status" kind="Sporadic" enable_multicast="true" layer="default" required_system_element="NO" is_simulink_interface="false" stack_size="340" queue_size="1" wcet="0" priority="1" miat="0">
    <Input_Parameter name="comms_mode_status_report" type="Comms-Mode-Status-Report-T" encoding="NATIVE"/>
    <Property name="Taste::InheritPI" value="true"/>
    <Property name="Taste::Autonamed" value="true"/>
</Required_Interface>

<Function id="{fbe2a4a5-96f4-4dad-be97-66a832021c09}" name="comms_mode_tracker" is_type="NO" is_visible="true" language="SDL" default_implementation="default" fixed_system_element="NO" required_system_element="NO" instances_max="1" instances_min="1" startup_priority="1" FPGA_Configurations="">
    <Property name="TASTE_IV_Properties::Default_Codegen" value="Ada"/>
<Provided_Interface id="{1022a016-a0fe-43aa-af04-b3901d011283}" name="change_comms_mode" kind="Sporadic" enable_multicast="true" layer="default" required_system_element="NO" is_simulink_interface="false" stack_size="340" queue_size="1" wcet="0" priority="1" miat="0">
    <Input_Parameter name="target_comms_mode" type="Comms-Mode-T" encoding="NATIVE"/>
</Provided_Interface>

<Required_Interface id="{1c067830-74ff-4e6d-99e5-b4af1b493685}" name="report_comms_mode_status" kind="Sporadic" enable_multicast="true" layer="default" required_system_element="NO" is_simulink_interface="false" stack_size="340" queue_size="1" wcet="0" priority="1" miat="0">
    <Input_Parameter name="comms_mode_status_report" type="Comms-Mode-Status-Report-T" encoding="NATIVE"/>
    <Property name="Taste::InheritPI" value="true"/>
    <Property name="Taste::Autonamed" value="true"/>
</Required_Interface>

    <Implementations>
        <Implementation name="default" language="SDL"/>
    </Implementations>
</Function>

<Connection id="{60b6d945-9aa6-4b22-83b6-ac8643bf297d}" name="comms_subsystem_change_comms_mode____comms_mode_tracker_change_comms_mode" required_system_element="NO">
    <Source func_name="comms_subsystem" pi_name="change_comms_mode" />
    <Target func_name="comms_mode_tracker" pi_name="change_comms_mode" />
</Connection>

<Connection id="{314234b8-d4e4-4974-8c18-01b276612d0a}" name="comms_mode_tracker_report_comms_mode_status____comms_subsystem_report_comms_mode_status" required_system_element="NO">
    <Source func_name="comms_mode_tracker" ri_name="report_comms_mode_status" />
    <Target func_name="comms_subsystem" ri_name="report_comms_mode_status" />
</Connection>

    <Implementations>
        <Implementation name="default" language="SDL"/>
    </Implementations>
</Function>

<Function id="{a5acb82c-debf-4095-96b3-08b67399c076}" name="payload_subsystem" is_type="NO" language="SDL" default_implementation="default" fixed_system_element="NO" required_system_element="NO" instances_max="1" instances_min="1" startup_priority="1">
    <Property name="TASTE_IV_Properties::Default_Codegen" value="Ada"/>
<Provided_Interface id="{b39541e9-71cb-4d5e-9171-91261976f233}" name="change_payload_mode" kind="Sporadic" enable_multicast="true" layer="default" required_system_element="NO" is_simulink_interface="false" stack_size="340" queue_size="1" wcet="0" priority="1" miat="0">
    <Input_Parameter name="target_payload_mode" type="Payload-Mode-T" encoding="NATIVE"/>
</Provided_Interface>

<Required_Interface id="{af2671e4-0339-4b40-b4ae-a88ee7382e68}" name="report_payload_mode_status" kind="Sporadic" enable_multicast="true" layer="default" required_system_element="NO" is_simulink_interface="false" stack_size="340" queue_size="1" wcet="0" priority="1" miat="0">
    <Input_Parameter name="payload_mode_status_report" type="Payload-Mode-Status-Report-T" encoding="NATIVE"/>
    <Property name="Taste::InheritPI" value="true"/>
    <Property name="Taste::Autonamed" value="true"/>
</Required_Interface>

<Function id="{155c111d-7661-4e5f-80e7-c60707828360}" name="payload_mode_tracker" is_type="NO" is_visible="true" language="SDL" default_implementation="default" fixed_system_element="NO" required_system_element="NO" instances_max="1" instances_min="1" startup_priority="1" FPGA_Configurations="">
    <Property name="TASTE_IV_Properties::Default_Codegen" value="Ada"/>
<Provided_Interface id="{d7d8cd6f-6bb8-4548-be22-146044f5a1e0}" name="change_payload_mode" kind="Sporadic" enable_multicast="true" layer="default" required_system_element="NO" is_simulink_interface="false" stack_size="340" queue_size="1" wcet="0" priority="1" miat="0">
    <Input_Parameter name="target_payload_mode" type="Payload-Mode-T" encoding="NATIVE"/>
</Provided_Interface>

<Required_Interface id="{c6018e36-342e-4666-b852-995c6eb935d3}" name="report_payload_mode_status" kind="Sporadic" enable_multicast="true" layer="default" required_system_element="NO" is_simulink_interface="false" stack_size="340" queue_size="1" wcet="0" priority="1" miat="0">
    <Input_Parameter name="payload_mode_status_report" type="Payload-Mode-Status-Report-T" encoding="NATIVE"/>
    <Property name="Taste::InheritPI" value="true"/>
    <Property name="Taste::Autonamed" value="true"/>
</Required_Interface>

    <Implementations>
        <Implementation name="default" language="SDL"/>
    </Implementations>
</Function>

<Connection id="{de6492f2-e6b0-4cc4-96a2-2ad858350544}" name="payload_subsystem_change_payload_mode____payload_mode_tracker_change_payload_mode" required_system_element="NO">
    <Source func_name="payload_subsystem" pi_name="change_payload_mode" />
    <Target func_name="payload_mode_tracker" pi_name="change_payload_mode" />
</Connection>

<Connection id="{60e2cb69-556f-4471-a473-b5b282988020}" name="payload_mode_tracker_report_payload_mode_status____payload_subsystem_report_payload_mode_status" required_system_element="NO">
    <Source func_name="payload_mode_tracker" ri_name="report_payload_mode_status" />
    <Target func_name="payload_subsystem" ri_name="report_payload_mode_status" />
</Connection>

    <Implementations>
        <Implementation name="default" language="SDL"/>
    </Implementations>
</Function>

<Function id="{d1cf631b-9c70-4dc2-b86d-8eec99c26aed}" name="adcs_subsystem" is_type="NO" language="SDL" default_implementation="default" fixed_system_element="NO" required_system_element="NO" instances_max="1" instances_min="1" startup_priority="1">
    <Property name="TASTE_IV_Properties::Default_Codegen" value="Ada"/>
<Provided_Interface id="{1f743119-0101-46af-be20-d28bb60ff948}" name="change_adcs_mode" kind="Sporadic" enable_multicast="true" layer="default" required_system_element="NO" is_simulink_interface="false" stack_size="340" queue_size="1" wcet="0" priority="1" miat="0">
    <Input_Parameter name="target_adcs_mode" type="ADCS-Mode-T" encoding="NATIVE"/>
</Provided_Interface>

<Required_Interface id="{0079b77e-4e9c-4828-b83a-4a4caebdcc77}" name="report_adcs_mode_status" kind="Sporadic" enable_multicast="true" layer="default" required_system_element="NO" is_simulink_interface="false" stack_size="340" queue_size="1" wcet="0" priority="1" miat="0">
    <Input_Parameter name="adcs_mode_status_report" type="ADCS-Mode-Status-Report-T" encoding="NATIVE"/>
    <Property name="Taste::InheritPI" value="true"/>
    <Property name="Taste::Autonamed" value="true"/>
</Required_Interface>

<Function id="{1d1a1901-5168-4308-a2da-1a09f84a2c42}" name="adcs_mode_tracker" is_type="NO" is_visible="true" language="SDL" default_implementation="default" fixed_system_element="NO" required_system_element="NO" instances_max="1" instances_min="1" startup_priority="1" FPGA_Configurations="">
    <Property name="TASTE_IV_Properties::Default_Codegen" value="Ada"/>
<Provided_Interface id="{2392e4b5-457c-4e63-a71e-e8e5d016d6f1}" name="change_adcs_mode" kind="Sporadic" enable_multicast="true" layer="default" required_system_element="NO" is_simulink_interface="false" stack_size="340" queue_size="1" wcet="0" priority="1" miat="0">
    <Input_Parameter name="target_adcs_mode" type="ADCS-Mode-T" encoding="NATIVE"/>
</Provided_Interface>

<Required_Interface id="{438c96b7-9fad-4532-b568-51d14cfc229a}" name="report_adcs_mode_status" kind="Sporadic" enable_multicast="true" layer="default" required_system_element="NO" is_simulink_interface="false" stack_size="340" queue_size="1" wcet="0" priority="1" miat="0">
    <Input_Parameter name="adcs_mode_status_report" type="ADCS-Mode-Status-Report-T" encoding="NATIVE"/>
    <Property name="Taste::InheritPI" value="true"/>
    <Property name="Taste::Autonamed" value="true"/>
</Required_Interface>

    <Implementations>
        <Implementation name="default" language="SDL"/>
    </Implementations>
</Function>

<Connection id="{827dac87-cd3f-4afd-ad46-ad3e40d20e9f}" name="adcs_subsystem_change_adcs_mode____adcs_mode_tracker_change_adcs_mode" required_system_element="NO">
    <Source func_name="adcs_subsystem" pi_name="change_adcs_mode" />
    <Target func_name="adcs_mode_tracker" pi_name="change_adcs_mode" />
</Connection>

<Connection id="{31f13eb2-02cb-48ee-b338-7acb114d844d}" name="adcs_mode_tracker_report_adcs_mode_status____adcs_subsystem_report_adcs_mode_status" required_system_element="NO">
    <Source func_name="adcs_mode_tracker" ri_name="report_adcs_mode_status" />
    <Target func_name="adcs_subsystem" ri_name="report_adcs_mode_status" />
</Connection>

    <Implementations>
        <Implementation name="default" language="SDL"/>
    </Implementations>
</Function>

<Function id="{a01995ae-6930-4f7d-83cd-a0808a08b960}" name="deployer_subsystem" is_type="NO" language="SDL" default_implementation="default" fixed_system_element="NO" required_system_element="NO" instances_max="1" instances_min="1" startup_priority="1">
    <Property name="TASTE_IV_Properties::Default_Codegen" value="Ada"/>
<Provided_Interface id="{6bf36c9a-d8f1-41dd-969f-1b4329f5c577}" name="change_deployer_mode" kind="Sporadic" enable_multicast="true" layer="default" required_system_element="NO" is_simulink_interface="false" stack_size="340" queue_size="1" wcet="0" priority="1" miat="0">
    <Input_Parameter name="target_deployer_mode" type="Deployer-Mode-T" encoding="NATIVE"/>
</Provided_Interface>

<Required_Interface id="{3dcedbca-90c4-4522-aec0-4ffbc8cf41ff}" name="report_deployer_mode_status" kind="Sporadic" enable_multicast="true" layer="default" required_system_element="NO" is_simulink_interface="false" stack_size="1024" queue_size="1" wcet="0" priority="1" miat="0">
    <Input_Parameter name="deployer_mode_status_report" type="Deployer-Mode-Status-Report-T" encoding="NATIVE"/>
    <Property name="Taste::InheritPI" value="true"/>
    <Property name="Taste::Autonamed" value="true"/>
</Required_Interface>

<Function id="{22d6f47e-bfcc-47d5-ba5a-b4e79f399e7e}" name="deployer_mode_tracker" is_type="NO" is_visible="true" language="SDL" default_implementation="default" fixed_system_element="NO" required_system_element="NO" instances_max="1" instances_min="1" startup_priority="1" FPGA_Configurations="">
    <Property name="TASTE_IV_Properties::Default_Codegen" value="Ada"/>
<Provided_Interface id="{1c8b24c4-29fd-44a9-a4e8-59ac26a6ea94}" name="change_deployer_mode" kind="Sporadic" enable_multicast="true" layer="default" required_system_element="NO" is_simulink_interface="false" stack_size="340" queue_size="1" wcet="0" priority="1" miat="0">
    <Input_Parameter name="target_deployer_mode" type="Deployer-Mode-T" encoding="NATIVE"/>
</Provided_Interface>

<Required_Interface id="{fc8833d8-b237-4927-b20b-d03f5ec473d7}" name="report_deployer_mode_status" kind="Sporadic" enable_multicast="true" layer="default" required_system_element="NO" is_simulink_interface="false" stack_size="1024" queue_size="1" wcet="0" priority="1" miat="0">
    <Input_Parameter name="deployer_mode_status_report" type="Deployer-Mode-Status-Report-T" encoding="NATIVE"/>
    <Property name="Taste::InheritPI" value="true"/>
    <Property name="Taste::Autonamed" value="true"/>
</Required_Interface>

    <Implementations>
        <Implementation name="default" language="SDL"/>
    </Implementations>
</Function>

<Connection id="{945d60b1-4c31-44c9-a0b3-710cc624b0fa}" name="deployer_subsystem_change_deployer_mode____deployer_mode_tracker_change_deployer_mode" required_system_element="NO">
    <Source func_name="deployer_subsystem" pi_name="change_deployer_mode" />
    <Target func_name="deployer_mode_tracker" pi_name="change_deployer_mode" />
</Connection>

<Connection id="{971421c5-6a0c-4170-bee0-f61543f42db3}" name="deployer_mode_tracker_report_deployer_mode_status____deployer_subsystem_report_deployer_mode_status" required_system_element="NO">
    <Source func_name="deployer_mode_tracker" ri_name="report_deployer_mode_status" />
    <Target func_name="deployer_subsystem" ri_name="report_deployer_mode_status" />
</Connection>

    <Implementations>
        <Implementation name="default" language="SDL"/>
    </Implementations>
</Function>

<Connection id="{3b278e35-6dde-4a87-bb22-40e79a59b711}" name="obc_subsystem_change_adcs_mode____adcs_subsystem_change_adcs_mode" required_system_element="NO">
    <Source func_name="obc_subsystem" ri_name="change_adcs_mode" />
    <Target func_name="adcs_subsystem" pi_name="change_adcs_mode" />
</Connection>

<Connection id="{5d87e370-a14c-4d34-a387-9977f4bf3f7d}" name="adcs_subsystem_report_adcs_mode_status____obc_subsystem_report_adcs_mode_status" required_system_element="NO">
    <Source func_name="adcs_subsystem" ri_name="report_adcs_mode_status" />
    <Target func_name="obc_subsystem" pi_name="report_adcs_mode_status" />
</Connection>

<Connection id="{2bf3ebd0-92b5-474c-8ea0-c7a41e2ca3f2}" name="obc_subsystem_change_pipeline_mode____pipeline_subsystem_change_pipeline_mode" required_system_element="NO">
    <Source func_name="obc_subsystem" ri_name="change_pipeline_mode" />
    <Target func_name="pipeline_subsystem" pi_name="change_pipeline_mode" />
</Connection>

<Connection id="{d3be9db5-f69b-4b49-ad87-47ce985e68b9}" name="gs_gui_tc_change_mission_mode____obc_subsystem_tc_change_mission_mode" required_system_element="NO">
    <Source func_name="gs_gui" ri_name="tc_change_mission_mode" />
    <Target func_name="obc_subsystem" pi_name="tc_change_mission_mode" />
</Connection>

<Connection id="{5aab5e78-9f53-4515-b79a-47ef174158a9}" name="obc_subsystem_change_comms_mode____comms_subsystem_change_comms_mode" required_system_element="NO">
    <Source func_name="obc_subsystem" ri_name="change_comms_mode" />
    <Target func_name="comms_subsystem" pi_name="change_comms_mode" />
</Connection>

<Connection id="{67f7aef9-ee4d-4699-8f20-579afacf23a0}" name="pipeline_subsystem_report_pipeline_mode_status____obc_subsystem_report_pipeline_mode_status" required_system_element="NO">
    <Source func_name="pipeline_subsystem" ri_name="report_pipeline_mode_status" />
    <Target func_name="obc_subsystem" pi_name="report_pipeline_mode_status" />
</Connection>

<Connection id="{4ba237ba-144c-4f9d-bf15-dd73f0c3ef0e}" name="obc_subsystem_change_deployer_mode____deployer_subsystem_change_deployer_mode" required_system_element="NO">
    <Source func_name="obc_subsystem" ri_name="change_deployer_mode" />
    <Target func_name="deployer_subsystem" pi_name="change_deployer_mode" />
</Connection>

<Connection id="{5c1bf957-f89f-4c1f-bd6c-84742e2dea26}" name="eps_subsystem_report_eps_mode_status____obc_subsystem_report_eps_mode_status" required_system_element="NO">
    <Source func_name="eps_subsystem" ri_name="report_eps_mode_status" />
    <Target func_name="obc_subsystem" pi_name="report_eps_mode_status" />
</Connection>

<Connection id="{8e5e9e01-05b3-4bbf-b3a6-b2a87e4ebbb2}" name="obc_subsystem_change_eps_mode____eps_subsystem_change_eps_mode" required_system_element="NO">
    <Source func_name="obc_subsystem" ri_name="change_eps_mode" />
    <Target func_name="eps_subsystem" pi_name="change_eps_mode" />
</Connection>

<Connection id="{47bd3432-b30c-45a7-9238-ca4476cdb5d8}" name="deployer_subsystem_report_deployer_mode_status____obc_subsystem_report_deployer_mode_status" required_system_element="NO">
    <Source func_name="deployer_subsystem" ri_name="report_deployer_mode_status" />
    <Target func_name="obc_subsystem" pi_name="report_deployer_mode_status" />
</Connection>

<Connection id="{34cd33c8-4409-4c34-9f3e-c6774fa7fe09}" name="comms_subsystem_report_comms_mode_status____obc_subsystem_report_comms_mode_status" required_system_element="NO">
    <Source func_name="comms_subsystem" ri_name="report_comms_mode_status" />
    <Target func_name="obc_subsystem" pi_name="report_comms_mode_status" />
</Connection>

<Connection id="{b9804151-3e3a-45bd-9ee0-e3d4149ada02}" name="payload_subsystem_report_payload_mode_status____obc_subsystem_report_payload_mode_status" required_system_element="NO">
    <Source func_name="payload_subsystem" ri_name="report_payload_mode_status" />
    <Target func_name="obc_subsystem" pi_name="report_payload_mode_status" />
</Connection>

<Connection id="{c7737474-63e3-4ec5-b1ee-061f7455854e}" name="obc_subsystem_report_mission_mode_change____gs_gui_report_mission_mode_change" required_system_element="NO">
    <Source func_name="obc_subsystem" ri_name="report_mission_mode_change" />
    <Target func_name="gs_gui" pi_name="report_mission_mode_change" />
</Connection>

<Connection id="{4e84295d-50ab-4d78-8f3c-8d5e5de14075}" name="obc_subsystem_change_payload_mode____payload_subsystem_change_payload_mode" required_system_element="NO">
    <Source func_name="obc_subsystem" ri_name="change_payload_mode" />
    <Target func_name="payload_subsystem" pi_name="change_payload_mode" />
</Connection>

<Comment id="{79126f59-8bdb-46a9-87c3-e562c108e91d}" name="Welcome to TASTE!\n============\n\nRight click to add a function, and use Ctrl-Click to connect functions together.\n\nYou can split the screen in multiple windows using Ctrl-E-3" is_visible="true" required_system_element="NO">
</Comment>

<Layer name="default" is_visible="true"/>

</InterfaceView>